evolution_opt/__init__.py
evolution_opt/genetic.py
evolution_opt-0.0.5.dist-info/LICENSE
evolution_opt-0.0.5.dist-info/METADATA
evolution_opt-0.0.5.dist-info/WHEEL
evolution_opt-0.0.5.dist-info/top_level.txt
evolution_opt-0.0.5.dist-info/RECORD
