Metadata-Version: 2.1
Name: evolution-opt
Version: 0.0.5
Summary: Evolution inspired optimisation algorithms
Home-page: https://github.com/eliottkalfon/evolution_opt
Author: Eliot Kalfon
Author-email: eliott.kalfon@gmail.com
License: UNKNOWN
Platform: UNKNOWN
Classifier: Programming Language :: Python :: 3
Classifier: License :: OSI Approved :: MIT License
Classifier: Operating System :: OS Independent
Requires-Python: >=3.6
